brikk/config/__init__.py
brikk/config/_lib.py
brikk/config/_types.py
brikk_config-0.2.2.dist-info/WHEEL
brikk_config-0.2.2.dist-info/METADATA
brikk_config-0.2.2.dist-info/RECORD
