Metadata-Version: 2.4
Name: brikk-config
Version: 0.2.2
Summary: brikk-config
Author: Lucino772
License-Expression: MIT
Requires-Dist: ruamel-yaml>=0.18.16 ; extra == 'yaml'
Requires-Python: >=3.10
Provides-Extra: yaml
